{
  "sections": {
    "16507112611d925512": {
      "type": "background-video",
      "disabled": true,
      "settings": {
        "section_size": "normal",
        "video_url": "https:\/\/youtu.be\/UevlNdJ9uZU"
      }
    },
    "16507112644f91fd39": {
      "type": "custom-html",
      "disabled": true,
      "settings": {
        "subheading": "",
        "title": "Welcome to Eddy",
        "html": "Pairing elevated California bohemia with global inspiration, Eddy is on a mission to consciously curate a whimsical world. One that helps you feel good on the inside and dress like it on the outside."
      }
    },
    "slideshow": {
      "type": "slideshow",
      "blocks": {
        "6b4f707c-3b5b-4d4c-93c7-e1c3c2719470": {
          "type": "image",
          "settings": {
            "image": "shopify:\/\/shop_images\/mttam_23009-511_4263_d9bb5d01-c5da-4c27-abbf-7b43ff6f8196.jpg",
            "mobile_image": "shopify:\/\/shop_images\/mttam_23009-511_4263_d9bb5d01-c5da-4c27-abbf-7b43ff6f8196.jpg",
            "apply_overlay": false,
            "content_position": "bottomLeft",
            "subheading": "",
            "title": "EXPLORE THE LATEST",
            "button_1_text": "",
            "button_1_link": "shopify:\/\/collections\/new-arrivals",
            "button_2_text": "",
            "button_2_link": ""
          }
        },
        "eb0b1c32-3a52-4ec6-a0ca-559e4e803bc5": {
          "type": "image",
          "settings": {
            "image": "shopify:\/\/shop_images\/Summer23-MtTam-23016-129-1180_908b0eaf-063e-4a55-b4ba-7f9499b78307.jpg",
            "mobile_image": "shopify:\/\/shop_images\/Summer23-MtTam-23016-129-1180_908b0eaf-063e-4a55-b4ba-7f9499b78307.jpg",
            "apply_overlay": false,
            "content_position": "bottomLeft",
            "subheading": "",
            "title": "",
            "button_1_text": "",
            "button_1_link": "",
            "button_2_text": "",
            "button_2_link": ""
          }
        },
        "dc7f34ab-8db9-4f1d-80d6-268e3748575b": {
          "type": "image",
          "settings": {
            "image": "shopify:\/\/shop_images\/MtTam_23012-608_1478_2_aba16868-3364-4ac7-89dc-cf25a8a59be9.jpg",
            "mobile_image": "shopify:\/\/shop_images\/MtTam_23012-608_1478_2_aba16868-3364-4ac7-89dc-cf25a8a59be9.jpg",
            "apply_overlay": false,
            "content_position": "bottomLeft",
            "subheading": "",
            "title": "",
            "button_1_text": "",
            "button_1_link": "https:\/\/shopeddy.com\/collections\/new-arrivals",
            "button_2_text": "",
            "button_2_link": ""
          }
        },
        "slide-0": {
          "type": "image",
          "settings": {
            "image": "shopify:\/\/shop_images\/MtTam_23093-129_0327.jpg",
            "mobile_image": "shopify:\/\/shop_images\/MtTam_23093-129_0327.jpg",
            "apply_overlay": false,
            "content_position": "bottomLeft",
            "subheading": "",
            "title": "",
            "button_1_text": "",
            "button_1_link": "https:\/\/shopeddy.com\/collections\/all",
            "button_2_text": "",
            "button_2_link": "https:\/\/shopeddy.com\/collections\/all"
          }
        },
        "cf27ba41-e092-4f95-9266-b967b4ed9688": {
          "type": "image",
          "settings": {
            "image": "shopify:\/\/shop_images\/MtTam_23097-107_6630.jpg",
            "mobile_image": "shopify:\/\/shop_images\/MtTam_23097-107_6630.jpg",
            "apply_overlay": false,
            "content_position": "bottomLeft",
            "subheading": "",
            "title": "",
            "button_1_text": "",
            "button_1_link": "https:\/\/shopeddy.com\/collections\/new-arrivals",
            "button_2_text": "",
            "button_2_link": ""
          }
        }
      },
      "block_order": [
        "6b4f707c-3b5b-4d4c-93c7-e1c3c2719470",
        "eb0b1c32-3a52-4ec6-a0ca-559e4e803bc5",
        "dc7f34ab-8db9-4f1d-80d6-268e3748575b",
        "slide-0",
        "cf27ba41-e092-4f95-9266-b967b4ed9688"
      ],
      "settings": {
        "show_fullscreen": true,
        "show_arrow": false,
        "autoplay": true,
        "cycle_speed": 4,
        "text_color": "#ffffff",
        "button_color": "#363636",
        "button_background": "#ffffff"
      }
    },
    "1650476318fd586541": {
      "type": "custom-html",
      "disabled": true,
      "settings": {
        "subheading": "",
        "title": "",
        "html": "<marquee truespeed=\"1\" scrollamount=\"12\">JOIN OUR MAILING LIST TO RECEIVE 10% OFF YOUR FIRST ORDER<\/marquee>"
      }
    },
    "collection-list": {
      "type": "collection-list",
      "blocks": {
        "collection-0": {
          "type": "collection",
          "settings": {
            "collection": "dresses",
            "image": "shopify:\/\/shop_images\/Summer23-MtTam-23016-250-5012.jpg",
            "image_alignment": "center center",
            "content_position": "bottomLeft",
            "subheading": "",
            "title": "DRESSES",
            "button_text": "View products",
            "button_link": "",
            "apply_overlay": true
          }
        },
        "collection-1": {
          "type": "collection",
          "settings": {
            "collection": "tops",
            "image": "shopify:\/\/shop_images\/Summer23-MtTam-23029-111-23019-111-0336.jpg",
            "image_alignment": "center center",
            "content_position": "bottomLeft",
            "subheading": "",
            "title": "Tops",
            "button_text": "View products",
            "button_link": "",
            "apply_overlay": true
          }
        },
        "collection-2": {
          "type": "collection",
          "settings": {
            "collection": "skirts",
            "image": "shopify:\/\/shop_images\/Summer23-MtTam-23031-112-23024-112-4660.jpg",
            "image_alignment": "center center",
            "content_position": "bottomLeft",
            "subheading": "",
            "title": "SKIRTS",
            "button_text": "View products",
            "button_link": "",
            "apply_overlay": true
          }
        },
        "5c7d12c3-cf5c-4207-87c2-56ecf6a43f78": {
          "type": "collection",
          "settings": {
            "collection": "blazers",
            "image": "shopify:\/\/shop_images\/Carmel_22081_23014_GROUP_3773-2_117a55f0-c698-40f7-b7a8-e8ff7c4a11de.jpg",
            "image_alignment": "center center",
            "content_position": "bottomLeft",
            "subheading": "",
            "title": "Outerwear & Sweaters",
            "button_text": "View products",
            "button_link": "",
            "apply_overlay": true
          }
        },
        "0f04bec7-f9c6-4fd3-a127-c1258f9d3798": {
          "type": "collection",
          "settings": {
            "collection": "sleepwear",
            "image": "shopify:\/\/shop_images\/mttam_23038-107_7043_86098744-44f1-45e7-b72c-ebc0dd518212.jpg",
            "image_alignment": "center center",
            "content_position": "bottomLeft",
            "subheading": "",
            "title": "Sleepwear",
            "button_text": "View products",
            "button_link": "",
            "apply_overlay": true
          }
        },
        "4716ea2f-fda4-4eda-9f46-6f9270dfc04a": {
          "type": "collection",
          "settings": {
            "collection": "accessories",
            "image": "shopify:\/\/shop_images\/Carmel_SILVER_BAG_0004.jpg",
            "image_alignment": "center center",
            "content_position": "bottomLeft",
            "subheading": "",
            "title": "Accessories",
            "button_text": "View products",
            "button_link": "",
            "apply_overlay": true
          }
        }
      },
      "block_order": [
        "collection-0",
        "collection-1",
        "collection-2",
        "5c7d12c3-cf5c-4207-87c2-56ecf6a43f78",
        "0f04bec7-f9c6-4fd3-a127-c1258f9d3798",
        "4716ea2f-fda4-4eda-9f46-6f9270dfc04a"
      ],
      "settings": {
        "image_size": "normal",
        "add_spacing": true,
        "expand_collection": false,
        "stack_on_mobile": true,
        "text_color": "#ffffff",
        "button_color": "#363636"
      }
    },
    "165079842840a1d8ce": {
      "type": "image-with-text-overlay",
      "settings": {
        "section_size": "large",
        "image": "shopify:\/\/shop_images\/Summer23-MtTam-23016-250-4867.jpg",
        "text_color": "#ffffff",
        "overlay_color": "#595959",
        "overlay_opacity": 22,
        "subheading": "",
        "title": "WELCOME TO EDDY",
        "content": "<p>Pairing elevated California bohemia with global inspiration, EDDY is on a mission to consciously curate a whimsical world. One that helps you feel good on the inside and dress like it on the outside.<\/p>"
      }
    },
    "165147731496201e33": {
      "type": "featured-collections",
      "disabled": true,
      "blocks": {
        "1651477314e930b694-0": {
          "type": "collection",
          "settings": {
            "collection": "new-arrivals",
            "title": "Brand new",
            "grid_items_count": 3,
            "button_text": "View all sleepwear"
          }
        }
      },
      "block_order": [
        "1651477314e930b694-0"
      ],
      "settings": {
        "title": "",
        "layout_mode": "grid",
        "show_product_info": true,
        "show_vendor": false,
        "show_color_swatch": false,
        "grid_mobile_items_per_row": "2",
        "grid_desktop_items_per_row": 3
      }
    },
    "1650711244533a7038": {
      "type": "text-with-image",
      "settings": {
        "subheading": "",
        "title": "MINI MOMENTS",
        "image": "shopify:\/\/shop_images\/Summer23-MtTam-23093-608-5424_4cb555e8-95c6-4dee-8578-1adc30c38638.jpg",
        "image_position": "right",
        "content": "",
        "link_text": "FOR YOUR GOLDEN HOUR GLOW",
        "link_url": "shopify:\/\/collections\/dresses"
      }
    },
    "6da4724e-df67-4ed8-b359-e8bcc428a7b1": {
      "type": "image-with-text-overlay",
      "settings": {
        "section_size": "large",
        "image": "shopify:\/\/shop_images\/Untitled_design-17_7773e8ca-c6f1-4735-8916-5ad6ae69b0b1.png",
        "text_color": "#ffffff",
        "overlay_color": "#000000",
        "overlay_opacity": 0,
        "subheading": "",
        "title": "A FLORAL INTRODUCTION",
        "content": "<p>EXPLORE <a href=\"\/collections\/new-arrivals\" title=\"New Arrivals\">NEW ARRIVALS<\/a><\/p>"
      }
    },
    "1650798452ef2a3dd2": {
      "type": "text-with-image",
      "settings": {
        "subheading": "",
        "title": "Business + Pleasure",
        "image": "shopify:\/\/shop_images\/Carmel_23034-603_22296.jpg",
        "image_position": "left",
        "content": "",
        "link_text": "Shop Outerwear",
        "link_url": "shopify:\/\/collections\/blazers"
      }
    },
    "5f602754-47b5-46d9-9946-f3419ee32656": {
      "type": "image-with-text-overlay",
      "settings": {
        "section_size": "large",
        "image": "shopify:\/\/shop_images\/MtTam_23093-129_0084_31a37394-45ab-4cbc-9940-ca464d23bb05.jpg",
        "text_color": "#ffffff",
        "overlay_color": "#595959",
        "overlay_opacity": 0,
        "subheading": "",
        "title": "SOMETHING TO TWIRL AROUND IN",
        "content": "<p><a href=\"\/collections\/dresses\" title=\"Dresses\">Shop Dresses<\/a><\/p>"
      }
    },
    "shop-the-look": {
      "type": "shop-the-look",
      "disabled": true,
      "blocks": {
        "look-0": {
          "type": "look",
          "settings": {
            "image": "shopify:\/\/shop_images\/Eddy-Holiday-SF-2022-Campaign-1863-k.jpg",
            "dot_style": "light",
            "product_1": "amber-beaded-fluted-skirt",
            "product_1_horizontal_position": 58,
            "product_1_vertical_position": 62,
            "product_2": "helen-tiered-maxi-dress-teal-cerise-floral",
            "product_2_horizontal_position": 78,
            "product_2_vertical_position": 70,
            "product_3": "helen-tiered-maxi-dress",
            "product_3_horizontal_position": 19,
            "product_3_vertical_position": 50
          }
        },
        "look-1": {
          "type": "look",
          "settings": {
            "image": "shopify:\/\/shop_images\/skirt0.jpg",
            "dot_style": "light",
            "product_1": "brook-embroidered-fluted-skirt",
            "product_1_horizontal_position": 42,
            "product_1_vertical_position": 34,
            "product_2": "beaded-floral-handbag",
            "product_2_horizontal_position": 52,
            "product_2_vertical_position": 45,
            "product_3": "trisha-tiered-skirt",
            "product_3_horizontal_position": 73,
            "product_3_vertical_position": 44
          }
        }
      },
      "block_order": [
        "look-0",
        "look-1"
      ],
      "settings": {
        "subheading": "Shop",
        "title": "Our looks",
        "show_mobile_product_info": false
      }
    }
  },
  "order": [
    "16507112611d925512",
    "16507112644f91fd39",
    "slideshow",
    "1650476318fd586541",
    "collection-list",
    "165079842840a1d8ce",
    "165147731496201e33",
    "1650711244533a7038",
    "6da4724e-df67-4ed8-b359-e8bcc428a7b1",
    "1650798452ef2a3dd2",
    "5f602754-47b5-46d9-9946-f3419ee32656",
    "shop-the-look"
  ]
}
